umakaviewer/__init__.py
umakaviewer/scripts/__init__.py
umakaviewer/scripts/services/__init__.py
umakaviewer/scripts/services/assets.py
umakaviewer/scripts/services/build.py
umakaviewer/scripts/services/convert.py
umakaviewer/scripts/services/utils.py
umakaviewer/services.py
umakaviewer-0.0.12.dist-info/entry_points.txt
umakaviewer-0.0.12.dist-info/WHEEL
umakaviewer-0.0.12.dist-info/METADATA
umakaviewer-0.0.12.dist-info/RECORD
