Metadata-Version: 2.1
Name: umakaviewer
Version: 0.0.12
Summary: 
Home-page: http://umaka-viewer.dbcls.jp/
License: MIT
Keywords: dbcls,rdf
Author: DBCLS
Requires-Python: >=2.7, !=3.0.*, !=3.1.*, !=3.2.*, !=3.3.*
Classifier: License :: OSI Approved :: MIT License
Classifier: Programming Language :: Python :: 2
Classifier: Programming Language :: Python :: 2.7
Classifier: Programming Language :: Python :: 3
Classifier: Programming Language :: Python :: 3.4
Classifier: Programming Language :: Python :: 3.5
Classifier: Programming Language :: Python :: 3.6
Classifier: Programming Language :: Python :: 3.7
Classifier: Programming Language :: Python :: 3.8
Requires-Dist: click (>=7.0,<8.0)
Requires-Dist: isodate (>=0.6.0,<0.7.0)
Requires-Dist: pyparsing (>=2.4,<3.0)
Requires-Dist: rdflib (>=4.2,<5.0)
Requires-Dist: tqdm (>=4.52.0,<5.0.0)
Project-URL: Repository, https://github.com/dbcls/umakaviewer
